blender_mcp/__init__.py
blender_mcp/server.py
blender_mcp_enhanced-1.3.3.dist-info/licenses/LICENSE
blender_mcp_enhanced-1.3.3.dist-info/METADATA
blender_mcp_enhanced-1.3.3.dist-info/WHEEL
blender_mcp_enhanced-1.3.3.dist-info/entry_points.txt
blender_mcp_enhanced-1.3.3.dist-info/top_level.txt
blender_mcp_enhanced-1.3.3.dist-info/RECORD
