Metadata-Version: 2.4
Name: blender-mcp-enhanced
Version: 1.3.3
Summary: Enhanced Blender integration through MCP with shared context, geometry nodes, and advanced tool chaining
Author-email: Zach Handley <zachhandley@gmail.com>
License: MIT
Project-URL: Homepage, https://github.com/ZachHandley/blender-mcp-enhanced
Project-URL: Repository, https://github.com/ZachHandley/blender-mcp-enhanced.git
Project-URL: Bug Tracker, https://github.com/ZachHandley/blender-mcp-enhanced/issues
Project-URL: Documentation, https://github.com/ZachHandley/blender-mcp-enhanced#readme
Project-URL: Changelog, https://github.com/ZachHandley/blender-mcp-enhanced/blob/main/CHANGELOG.md
Keywords: blender,mcp,ai,3d,modeling,geometry-nodes,procedural
Classifier: Development Status :: 4 - Beta
Classifier: Programming Language :: Python :: 3
Classifier: Programming Language :: Python :: 3.10
Classifier: Programming Language :: Python :: 3.11
Classifier: Programming Language :: Python :: 3.12
Classifier: License :: OSI Approved :: MIT License
Classifier: Operating System :: OS Independent
Classifier: Topic :: Multimedia :: Graphics :: 3D Modeling
Classifier: Topic :: Scientific/Engineering :: Artificial Intelligence
Classifier: Intended Audience :: Developers
Classifier: Intended Audience :: End Users/Desktop
Requires-Python: >=3.10
License-File: LICENSE
Requires-Dist: mcp[cli]>=1.3.0
Provides-Extra: dev
Requires-Dist: build; extra == "dev"
Requires-Dist: twine; extra == "dev"
Requires-Dist: pytest; extra == "dev"
Dynamic: license-file
